Verilog-Codes-main/Lab3/FullAdderNormal.v
module full_adder (
    input a,
    input b,
    input cin,
    output sum,
    output cout
);
    assign sum = a ^ b ^ cin;
    assign cout = (a & b) | (b & cin) | (a & cin);
endmodule

module tb_full_adder;
    reg A, B, Cin;
    wire Sum, Cout;

    full_adder uut (
        .a(A),
        .b(B),
        .cin(Cin),
        .sum(Sum),
        .cout(Cout)
    );

    initial begin
        $dumpfile("FullAdder.vcd");
        $dumpvars(0, tb_full_adder);
        $display("A B Cin | Sum Cout");
        
        A=0; B=0; Cin=0; #1 $display("%b %b  %b  |  %b    %b", A, B, Cin, Sum, Cout);
        A=0; B=0; Cin=1; #1 $display("%b %b  %b  |  %b    %b", A, B, Cin, Sum, Cout);
        A=0; B=1; Cin=0; #1 $display("%b %b  %b  |  %b    %b", A, B, Cin, Sum, Cout);
        A=0; B=1; Cin=1; #1 $display("%b %b  %b  |  %b    %b", A, B, Cin, Sum, Cout);
        A=1; B=0; Cin=0; #1 $display("%b %b  %b  |  %b    %b", A, B, Cin, Sum, Cout);
        A=1; B=0; Cin=1; #1 $display("%b %b  %b  |  %b    %b", A, B, Cin, Sum, Cout);
        A=1; B=1; Cin=0; #1 $display("%b %b  %b  |  %b    %b", A, B, Cin, Sum, Cout);
        A=1; B=1; Cin=1; #1 $display("%b %b  %b  |  %b    %b", A, B, Cin, Sum, Cout);

        $finish;
    end
endmodule

Verilog-Codes-main/Lab3/FullAdder.vcd
$date
	Mon Sep  8 01:34:38 2025
$end
$version
	Icarus Verilog
$end
$timescale
	1s
$end
$scope module tb_full_adder $end
$var wire 1 ! Sum $end
$var wire 1 " Cout $end
$var reg 1 # A $end
$var reg 1 $ B $end
$var reg 1 % Cin $end
$scope module uut $end
$var wire 1 # a $end
$var wire 1 $ b $end
$var wire 1 % cin $end
$var wire 1 " cout $end
$var wire 1 ! sum $end
$upscope $end
$upscope $end
$enddefinitions $end
$comment Show the parameter values. $end
$dumpall
$end
#0
$dumpvars
0%
0$
0#
0"
0!
$end
#1
1!
1%
#2
0%
1$
#3
1"
0!
1%
#4
0"
1!
0%
0$
1#
#5
1"
0!
1%
#6
0%
1$
#7
1!
1%
